README.md
setup.cfg
setup.py
docums_toc_sidebar_plugin/__init__.py
docums_toc_sidebar_plugin/plugin.py
docums_toc_sidebar_plugin.egg-info/PKG-INFO
docums_toc_sidebar_plugin.egg-info/SOURCES.txt
docums_toc_sidebar_plugin.egg-info/dependency_links.txt
docums_toc_sidebar_plugin.egg-info/entry_points.txt
docums_toc_sidebar_plugin.egg-info/requires.txt
docums_toc_sidebar_plugin.egg-info/top_level.txt